Metadata-Version: 1.0
Name: zone2gandi
Version: 0.1.1
Summary: Utility to push zone files up to Gandi DNS.
Home-page: https://gitlab.com/lyda/zone2gandi
Author: Kevin Lyda
Author-email: kevin@ie.suberic.net
License: UNKNOWN
Platform: UNKNOWN
